{
    "name": "Garden_Ground",
    "components": {
        "Transform": {
            "position": [
                -2.0363,
                -1.629207E-08,
                0.1
            ],
            "rotation": [
                2.504479E-06,
                0,
                0
            ],
            "scale": [
                0.01,
                0.01,
                0.01
            ]
        },
        "MeshFilter": {
            "pack": "./asset/model/meshes/Garden_Ground.FBX"
        },
        "MeshRenderer": {
            "material": {
                "textures": {
                    "material.albedo": "./asset/model/textures/Grass_AlbedoTransparency.png",
                    "material.metallic": "./asset/model/textures/Grass_MetallicSmoothness.png",
                    "material.normal": "./asset/model/textures/Grass_Normal.png",
                    "material.ao": "./asset/model/textures/Grass_AO.png"
                }
            },
            "shader": "pbr",
            "drawmode": "triangles"
        }
    },
    "isDeferred": true
}